gpstime/__init__.py
gpstime/__main__.py
gpstime/__version__.py
gpstime/leaps.py
gpstime/test.py
p1_gpstime-0.8.3.dev2.data/scripts/gpstime
p1_gpstime-0.8.3.dev2.dist-info/licenses/COPYING
p1_gpstime-0.8.3.dev2.dist-info/licenses/COPYING-GPL-3
p1_gpstime-0.8.3.dev2.dist-info/METADATA
p1_gpstime-0.8.3.dev2.dist-info/WHEEL
p1_gpstime-0.8.3.dev2.dist-info/top_level.txt
p1_gpstime-0.8.3.dev2.dist-info/RECORD
