Metadata-Version: 2.4
Name: p1-gpstime
Version: 0.8.3.dev2
Summary: GPS-aware datetime module
Author-email: Jameson Graef Rollins <jameson.rollins@ligo.org>
License-Expression: GPL-3.0-or-later
Project-URL: Homepage, https://git.ligo.org/cds/software/gpstime
Project-URL: Alternate, https://github.com/PointOneNav/gpstime
Classifier: Development Status :: 5 - Production/Stable
Classifier: Natural Language :: English
Classifier: Operating System :: OS Independent
Classifier: Programming Language :: Python
Classifier: Programming Language :: Python :: 3
Requires-Python: >=3.6
License-File: COPYING
License-File: COPYING-GPL-3
Requires-Dist: platformdirs; python_version >= "3.10"
Requires-Dist: appdirs; python_version < "3.10"
Requires-Dist: python-dateutil
Requires-Dist: requests
Dynamic: license-file
